task1/lfsr.sv
module lfsr (
        input logic         clk,    //input clock
        input logic         rst,     //reset
        input logic         en,     //enable
        output logic         [3:0] data_out     //serial data out 
);

        logic [4:1] sreg;       //shift register

        always_ff @ (posedge clk, posedge rst)
            if (rst)
                sreg <= 4'b1;
            else begin
                sreg <= en ? {sreg[3:1], sreg[3] ^ sreg[4] } : sreg;
            end
        assign data_out = sreg[4:1];

endmodule

task1/lfsr.vcd
$version Generated by VerilatedVcd $end
$date Thu Nov 17 02:35:20 2022 $end
$timescale 1ps $end

 $scope module TOP $end
  $var wire  1 # clk $end
  $var wire  4 & data_out [3:0] $end
  $var wire  1 % en $end
  $var wire  1 $ rst $end
  $scope module lfsr $end
   $var wire  1 # clk $end
   $var wire  4 & data_out [3:0] $end
   $var wire  1 % en $end
   $var wire  1 $ rst $end
   $var wire  4 ' sreg [4:1] $end
  $upscope $end
 $upscope $end
$enddefinitions $end


#0
0#
0$
1%
b0000 &
b0000 '
#1
1#
#2
0#
1$
0%
#3
1#
b0001 &
b0001 '
#4
0#
#5
1#
#6
0#
0$
#7
1#
#8
0#
#9
1#
#10
0#
#11
1#
#12
0#
#13
1#
#14
0#
#15
1#
#16
0#
#17
1#
#18
0#
#19
1#
#20
0#
#21
1#
#22
0#
#23
1#
#24
0#
#25
1#
#26
0#
#27
1#
#28
0#
#29
1#
#30
0#
#31
1#
#32
0#
#33
1#
#34
0#
#35
1#
#36
0#
#37
1#
#38
0#
#39
1#
#40
0#
#41
1#
#42
0#
#43
1#
#44
0#
#45
1#
#46
0#
#47
1#
#48
0#
#49
1#
#50
0#
#51
1#
#52
0#
#53
1#
#54
0#
#55
1#
#56
0#
#57
1#
#58
0#
#59
1#
#60
0#
#61
1#
#62
0#
#63
1#
#64
0#
#65
1#
#66
0#
#67
1#
#68
0#
#69
1#
#70
0#
#71
1#
#72
0#
#73
1#
#74
0#
#75
1#
#76
0#
#77
1#
#78
0#
#79
1#
#80
0#
#81
1#
#82
0#
#83
1#
#84
0#
#85
1#
#86
0#
#87
1#
#88
0#
#89
1#
#90
0#
#91
1#
#92
0#
#93
1#
#94
0#
#95
1#
#96
0#
#97
1#
#98
0#
#99
1#
#100
0#
#101
1#
#102
0#
#103
1#
#104
0#
#105
1#
#106
0#
#107
1#
#108
0#
#109
1#
#110
0#
#111
1#
#112
0#
#113
1#
#114
0#
#115
1#
#116
0#
#117
1#
#118
0#
#119
1#
#120
0#
#121
1#
#122
0#
#123
1#
#124
0#
#125
1#
#126
0#
#127
1#
#128
0#
#129
1#
#130
0#
#131
1#
#132
0#
#133
1#
#134
0#
#135
1#
#136
0#
#137
1#
#138
0#
#139
1#
#140
0#
#141
1#
#142
0#
#143
1#
#144
0#
#145
1#
#146
0#
#147
1#
#148
0#
#149
1#
#150
0#
#151
1#
#152
0#
#153
1#
#154
0#
#155
1#
#156
0#
#157
1#
#158
0#
#159
1#
#160
0#
#161
1#
#162
0#
#163
1#
#164
0#
#165
1#
#166
0#
#167
1#
#168
0#
#169
1#
#170
0#
#171
1#
#172
0#
#173
1#
#174
0#
#175
1#
#176
0#
#177
1#
#178
0#
#179
1#
#180
0#
#181
1#
#182
0#
#183
1#
#184
0#
#185
1#
#186
0#
#187
1#
#188
0#
#189
1#
#190
0#
#191
1#
#192
0#
#193
1#
#194
0#
#195
1#
#196
0#
#197
1#
#198
0#
#199
1#
#200
0#
#201
1#
#202
0#
#203
1#
#204
0#
#205
1#
#206
0#
#207
1#
#208
0#
#209
1#
#210
0#
#211
1#
#212
0#
#213
1#
#214
0#
#215
1#
#216
0#
#217
1#
#218
0#
#219
1#
#220
0#
#221
1#
#222
0#
#223
1#
#224
0#
#225
1#
#226
0#
#227
1#
#228
0#
#229
1#
#230
0#
#231
1#
#232
0#
#233
1#
#234
0#
#235
1#
#236
0#
#237
1#
#238
0#
#239
1#
#240
0#
#241
1#
#242
0#
#243
1#
#244
0#
#245
1#
#246
0#
#247
1#
#248
0#
#249
1#
#250
0#
#251
1#
#252
0#
#253
1#
#254
0#
#255
1#
#256
0#
#257
1#
#258
0#
#259
1#
#260
0#
#261
1#
#262
0#
#263
1#
#264
0#
#265
1#
#266
0#
#267
1#
#268
0#
#269
1#
#270
0#
#271
1#
#272
0#
#273
1#
#274
0#
#275
1#
#276
0#
#277
1#
#278
0#
#279
1#
#280
0#
#281
1#
#282
0#
#283
1#
#284
0#
#285
1#
#286
0#
#287
1#
#288
0#
#289
1#
#290
0#
#291
1#
#292
0#
#293
1#
#294
0#
#295
1#
#296
0#
#297
1#
#298
0#
#299
1#
#300
0#
#301
1#
#302
0#
#303
1#
#304
0#
#305
1#
#306
0#
#307
1#
#308
0#
#309
1#
#310
0#
#311
1#
#312
0#
#313
1#
#314
0#
#315
1#
#316
0#
#317
1#
#318
0#
#319
1#
#320
0#
#321
1#
#322
0#
#323
1#
#324
0#
#325
1#
#326
0#
#327
1#
#328
0#
#329
1#
#330
0#
#331
1#
#332
0#
#333
1#
#334
0#
#335
1#
#336
0#
#337
1#
#338
0#
#339
1#
#340
0#
#341
1#
#342
0#
#343
1#
#344
0#
#345
1#
#346
0#
#347
1#
#348
0#
#349
1#
#350
0#
#351
1#
#352
0#
#353
1#
#354
0#
#355
1#
#356
0#
#357
1#
#358
0#
#359
1#
#360
0#
1%
#361
1#
b0010 &
b0010 '
#362
0#
0%
#363
1#
#364
0#
#365
1#
#366
0#
#367
1#
#368
0#
#369
1#
#370
0#
#371
1#
#372
0#
#373
1#
#374
0#
#375
1#
#376
0#
#377
1#
#378
0#
#379
1#
#380
0#
#381
1#
#382
0#
#383
1#
#384
0#
#385
1#
#386
0#
#387
1#
#388
0#
#389
1#
#390
0#
#391
1#
#392
0#
#393
1#
#394
0#
#395
1#
#396
0#
#397
1#
#398
0#
#399
1#
#400
0#
#401
1#
#402
0#
#403
1#
#404
0#
#405
1#
#406
0#
#407
1#
#408
0#
#409
1#
#410
0#
#411
1#
#412
0#
#413
1#
#414
0#
#415
1#
#416
0#
#417
1#
#418
0#
#419
1#
#420
0#
#421
1#
#422
0#
#423
1#
#424
0#
#425
1#
#426
0#
#427
1#
#428
0#
#429
1#
#430
0#
#431
1#
#432
0#
#433
1#
#434
0#
#435
1#
#436
0#
#437
1#
#438
0#
#439
1#
#440
0#
#441
1#
#442
0#
#443
1#
#444
0#
#445
1#
#446
0#
#447
1#
#448
0#
#449
1#
#450
0#
#451
1#
#452
0#
#453
1#
#454
0#
#455
1#
#456
0#
#457
1#
#458
0#
#459
1#
#460
0#
#461
1#
#462
0#
#463
1#
#464
0#
#465
1#
#466
0#
#467
1#
#468
0#
#469
1#
#470
0#
#471
1#
#472
0#
#473
1#
#474
0#
#475
1#
#476
0#
#477
1#
#478
0#
#479
1#
#480
0#
#481
1#
#482
0#
#483
1#
#484
0#
1%
#485
1#
b0100 &
b0100 '
#486
0#
0%
