task2/f1_fsm.sv
module f1_fsm (
        input logic         clk,    //input clock
        input logic         rst,     //reset
        input logic         en,     //enable
        output logic        [7:0] data_out     //serial data out 
);
        //define states
        typedef enum {S0, S1, S2, S3, S4, S5, S6, S7, S8} my_state;
        my_state current_state, next_state;

        // state registers
        always_ff @ (posedge clk, posedge rst)
            if (rst)    current_state <= S0;
            else        current_state <= en ? next_state : current_state;

        always_comb 
            case (current_state)
                    S0: begin next_state = S1; data_out = 8'b0; end
                    S1: begin next_state = S2; data_out = 8'b1; end
                    S2: begin next_state = S3; data_out = 8'b11; end
                    S3: begin next_state = S4; data_out = 8'b111; end
                    S4: begin next_state = S5; data_out = 8'b1111; end
                    S5: begin next_state = S6; data_out = 8'b11111; end
                    S6: begin next_state = S7; data_out = 8'b111111; end
                    S7: begin next_state = S8; data_out = 8'b1111111; end
                    S8: begin next_state = S0; data_out = 8'b11111111; end
                    default: begin next_state = S0; data_out = 8'b0; end
            endcase

endmodule

task2/f1_fsm.vcd
$version Generated by VerilatedVcd $end
$date Thu Nov 17 03:18:57 2022 $end
$timescale 1ps $end

 $scope module TOP $end
  $var wire  1 # clk $end
  $var wire  8 & data_out [7:0] $end
  $var wire  1 % en $end
  $var wire  1 $ rst $end
  $scope module f1_fsm $end
   $var wire  1 # clk $end
   $var wire 32 ' current_state [31:0] $end
   $var wire  8 & data_out [7:0] $end
   $var wire  1 % en $end
   $var wire 32 ( next_state [31:0] $end
   $var wire  1 $ rst $end
  $upscope $end
 $upscope $end
$enddefinitions $end


#0
0#
0$
1%
b00000000 &
b00000000000000000000000000000000 '
b00000000000000000000000000000000 (
#1
1#
b00000000000000000000000000000001 (
#2
0#
1$
0%
#3
1#
#4
0#
#5
1#
#6
0#
0$
#7
1#
#8
0#
#9
1#
#10
0#
#11
1#
#12
0#
#13
1#
#14
0#
#15
1#
#16
0#
#17
1#
#18
0#
#19
1#
#20
0#
#21
1#
#22
0#
#23
1#
#24
0#
#25
1#
#26
0#
#27
1#
#28
0#
#29
1#
#30
0#
#31
1#
#32
0#
#33
1#
#34
0#
#35
1#
#36
0#
#37
1#
#38
0#
#39
1#
#40
0#
#41
1#
#42
0#
#43
1#
#44
0#
#45
1#
#46
0#
#47
1#
#48
0#
#49
1#
#50
0#
#51
1#
#52
0#
#53
1#
#54
0#
#55
1#
#56
0#
#57
1#
#58
0#
#59
1#
#60
0#
#61
1#
#62
0#
#63
1#
#64
0#
#65
1#
#66
0#
#67
1#
#68
0#
#69
1#
#70
0#
#71
1#
#72
0#
#73
1#
#74
0#
#75
1#
#76
0#
#77
1#
#78
0#
#79
1#
#80
0#
#81
1#
#82
0#
#83
1#
#84
0#
#85
1#
#86
0#
#87
1#
#88
0#
#89
1#
#90
0#
#91
1#
#92
0#
#93
1#
#94
0#
#95
1#
#96
0#
#97
1#
#98
0#
#99
1#
#100
0#
#101
1#
#102
0#
#103
1#
#104
0#
#105
1#
#106
0#
#107
1#
#108
0#
#109
1#
#110
0#
#111
1#
#112
0#
#113
1#
#114
0#
#115
1#
#116
0#
#117
1#
#118
0#
#119
1#
#120
0#
#121
1#
#122
0#
#123
1#
#124
0#
#125
1#
#126
0#
#127
1#
#128
0#
#129
1#
#130
0#
#131
1#
#132
0#
#133
1#
#134
0#
#135
1#
#136
0#
1%
#137
1#
b00000001 &
b00000000000000000000000000000001 '
b00000000000000000000000000000010 (
#138
0#
0%
#139
1#
#140
0#
#141
1#
#142
0#
#143
1#
#144
0#
#145
1#
#146
0#
#147
1#
#148
0#
#149
1#
#150
0#
#151
1#
#152
0#
#153
1#
#154
0#
#155
1#
#156
0#
#157
1#
#158
0#
#159
1#
#160
0#
#161
1#
#162
0#
#163
1#
#164
0#
#165
1#
#166
0#
#167
1#
#168
0#
#169
1#
#170
0#
#171
1#
#172
0#
#173
1#
#174
0#
#175
1#
#176
0#
#177
1#
#178
0#
#179
1#
#180
0#
#181
1#
#182
0#
#183
1#
#184
0#
#185
1#
#186
0#
#187
1#
#188
0#
#189
1#
#190
0#
#191
1#
#192
0#
1%
#193
1#
b00000011 &
b00000000000000000000000000000010 '
b00000000000000000000000000000011 (
#194
0#
0%
